.gitignore
.gitlab-ci.yml
CMakeLists.txt
LICENSE.md
README.md
config.h.cmake
dune-vem.pc.in
dune.module
pyproject.toml
setup.py
stamp-vc
cmake/modules/.gitignore
cmake/modules/CMakeLists.txt
cmake/modules/DuneVemMacros.cmake
data/genPerturbedMesh.m
data/genmesh.m
data/meshdata.mat
data/partitioned-mesh.msh
data/rd.m
data/shpfun.m
data/test.msh
data/testmesh2.msh
data/unitcube-2d-unstr.geo
data/unitcube-2d-unstr.msh
data/unitcube-2d.dgf
data/PolyMesher/GenPolyMesh.m
data/PolyMesher/HornDomain.m
data/PolyMesher/MbbDomain.m
data/PolyMesher/MichellDomain.m
data/PolyMesher/PolyMesher.m
data/PolyMesher/SuspensionDomain.m
data/PolyMesher/UnitSqDomain.m
data/PolyMesher/WrenchDomain.m
data/PolyMesher/barycentreOfPolygon.m
data/PolyMesher/dCircle.m
data/PolyMesher/dDiff.m
data/PolyMesher/dIntersect.m
data/PolyMesher/dLine.m
data/PolyMesher/dRectangle.m
data/PolyMesher/dUnion.m
data/PolyMesher/meshes/polymesher-mesh.msh
data/PolyMesher/meshes/test-meshes/mesh-1024-polygons.msh
data/PolyMesher/meshes/test-meshes/mesh-128-polygons.msh
data/PolyMesher/meshes/test-meshes/mesh-16-polygons.msh
data/PolyMesher/meshes/test-meshes/mesh-2048-polygons.msh
data/PolyMesher/meshes/test-meshes/mesh-256-polygons.msh
data/PolyMesher/meshes/test-meshes/mesh-32-polygons.msh
data/PolyMesher/meshes/test-meshes/mesh-4-polygons.msh
data/PolyMesher/meshes/test-meshes/mesh-512-polygons.msh
data/PolyMesher/meshes/test-meshes/mesh-64-polygons.msh
data/PolyMesher/meshes/test-meshes/mesh-8-polygons.msh
data/gmsh/CMakeLists.txt
data/gmsh/mymesh.msh
data/gmsh/unit_sq_4x4_npart=4.msh
data/gmsh/unit_sq_8x8_npart=16.msh
data/gmsh/unit_sq_8x8_npart=2.msh
data/gmsh/unit_sq_8x8_npart=4.msh
data/gmsh/unitsq-tria-unstr_npart=16.msh
dune/CMakeLists.txt
dune/vem/CMakeLists.txt
dune/vem/agglomeration/CMakeLists.txt
dune/vem/agglomeration/agglomeration.hh
dune/vem/agglomeration/basisfunctionset.hh
dune/vem/agglomeration/boundingbox.hh
dune/vem/agglomeration/dgmapper.hh
dune/vem/agglomeration/dgspace.hh
python/dune_vem.egg-info/PKG-INFO
python/dune_vem.egg-info/SOURCES.txt
python/dune_vem.egg-info/dependency_links.txt
python/dune_vem.egg-info/requires.txt
python/dune_vem.egg-info/top_level.txt