Metadata-Version: 2.1
Name: dune-vem
Version: 2.9.0.2
Summary: Implementation of a number of virtual element spaces and bilinear forms
Home-page: https://gitlab.dune-project.org/dune-fem/dune-vem
Author: Andreas Dedner
Author-email: a.s.dedner@warwick.ac.uk
License: UNKNOWN
Platform: UNKNOWN
Classifier: Programming Language :: C++
Classifier: Programming Language :: Python :: 3
Classifier: License :: OSI Approved :: GNU General Public License (GPL)
Requires-Python: >=3.4
License-File: LICENSE.md
